isingnetworks.py
isingnetworks-1.1.4.dist-info/LICENSE.txt
isingnetworks-1.1.4.dist-info/METADATA
isingnetworks-1.1.4.dist-info/WHEEL
isingnetworks-1.1.4.dist-info/top_level.txt
isingnetworks-1.1.4.dist-info/RECORD
