Metadata-Version: 2.1
Name: isingnetworks
Version: 1.1.4
Summary: This package is the implementation of the Ising Model on complex networks.
Home-page: https://github.com/Arnab-Gupta/ising-networks
Author: Arnab Gupta
Author-email: guptaarnab639@gmail.com
License: UNKNOWN
Platform: UNKNOWN
